newlandlib/__init__.py
newlandlib/common.py
newlandlib/fm100.py
newlandlib/serial_device.py
newlandlib/serial_threaded_device.py
newlandlib/version.py
trimarlib_newland-0.1.0rc4.dist-info/METADATA
trimarlib_newland-0.1.0rc4.dist-info/RECORD
trimarlib_newland-0.1.0rc4.dist-info/WHEEL
trimarlib_newland-0.1.0rc4.dist-info/top_level.txt
