Metadata-Version: 2.1
Name: trimarlib-newland
Version: 0.1.0rc4
Summary: Newland scanners library
Home-page: https://dsl2.trimar.org/pythons-ll/newlandlib
Author: TRIMAR Developer
Author-email: developer@trimar.com.pl
License: UNKNOWN
Platform: UNKNOWN
Classifier: Development Status :: 3 - Alpha
Classifier: License :: OSI Approved :: MIT License
Classifier: Natural Language :: English
Classifier: Operating System :: OS Independent
Classifier: Programming Language :: Python :: 3
Classifier: Topic :: Software Development :: Embedded Systems
Classifier: Topic :: Software Development :: Libraries :: Python Modules
Requires-Dist: pyserial
